{"cameraMode":{"drawMode":0,"name":"Shaded","section":"Shading Mode"},"sceneLighting":true,"audioPlay":false,"sceneViewState":{"m_AlwaysRefresh":false,"showFog":true,"showSkybox":true,"showFlares":true,"showImageEffects":true,"showParticleSystems":true,"showVisualEffectGraphs":true,"m_FxEnabled":true},"in2DMode":false,"pivot":{"x":-182.162353515625,"y":-142.82354736328126,"z":2927.613525390625},"rotation":{"x":0.008710674941539765,"y":-0.9906304478645325,"z":0.07653911411762238,"w":0.112812839448452},"size":547.3572998046875,"orthographic":false}